gsl_protocol_python/__init__.py
gsl_protocol_python/__main__.py
gsl_protocol_python/python.yaml
gsl_protocol_python/python_target.py
hedgehog/__init__.py
hedgehog/protocol/__init__.py
hedgehog/protocol/errors.py
hedgehog/protocol/messages/__init__.py
hedgehog/protocol/messages/ack.py
hedgehog/protocol/messages/analog.py
hedgehog/protocol/messages/digital.py
hedgehog/protocol/messages/emergency.py
hedgehog/protocol/messages/imu.py
hedgehog/protocol/messages/io.py
hedgehog/protocol/messages/motor.py
hedgehog/protocol/messages/process.py
hedgehog/protocol/messages/servo.py
hedgehog/protocol/messages/speaker.py
hedgehog/protocol/messages/version.py
hedgehog/protocol/proto/__init__.py
hedgehog/protocol/proto/ack_pb2.py
hedgehog/protocol/proto/analog_pb2.py
hedgehog/protocol/proto/digital_pb2.py
hedgehog/protocol/proto/emergency_pb2.py
hedgehog/protocol/proto/hedgehog_pb2.py
hedgehog/protocol/proto/imu_pb2.py
hedgehog/protocol/proto/io_pb2.py
hedgehog/protocol/proto/motor_pb2.py
hedgehog/protocol/proto/process_pb2.py
hedgehog/protocol/proto/servo_pb2.py
hedgehog/protocol/proto/speaker_pb2.py
hedgehog/protocol/proto/subscription_pb2.py
hedgehog/protocol/proto/version_pb2.py
hedgehog/protocol/zmq/__init__.py
hedgehog/protocol/zmq/asyncio.py
hedgehog/protocol/zmq/trio.py
hedgehog_protocol-0.9.0.dist-info/LICENSE
hedgehog_protocol-0.9.0.dist-info/METADATA
hedgehog_protocol-0.9.0.dist-info/WHEEL
hedgehog_protocol-0.9.0.dist-info/entry_points.txt
hedgehog_protocol-0.9.0.dist-info/top_level.txt
hedgehog_protocol-0.9.0.dist-info/RECORD
