Metadata-Version: 2.1
Name: hedgehog-protocol
Version: 0.9.0
Summary: Python Protocol definitions for Hedgehog
Home-page: https://github.com/PRIArobotics/HedgehogProtocol
Author: Clemens Koza
Author-email: koza@pria.at
License: AGPLv3+
Keywords: hedgehog robotics protobuf zmq protocol
Platform: UNKNOWN
Classifier: Development Status :: 4 - Beta
Classifier: Intended Audience :: Developers
Classifier: Topic :: Software Development
Classifier: License :: OSI Approved :: GNU Affero General Public License v3 or later (AGPLv3+)
Classifier: Programming Language :: Python :: 3
Requires-Dist: hedgehog-utils[protobuf,trio,zmq] (~=0.7.0rc1)
Provides-Extra: dev
Requires-Dist: invoke ; extra == 'dev'
Requires-Dist: hedgehog-protocol-spec (~=0.9.0) ; extra == 'dev'
Requires-Dist: pytest ; extra == 'dev'
Requires-Dist: pytest-runner ; extra == 'dev'
Requires-Dist: pytest-asyncio ; extra == 'dev'
Requires-Dist: pytest-trio ; extra == 'dev'
Requires-Dist: pytest-cov ; extra == 'dev'
Requires-Dist: pytest-timeout ; extra == 'dev'
Requires-Dist: mypy ; extra == 'dev'
